project/rtl/engine_position/angle_interpolator.v
//==============================================================================
// Módulo: angle_interpolator
//
// Descrição:
// Estima continuamente a posição angular do virabrequim entre dois dentes
// consecutivos da roda fônica.
//
// O módulo utiliza como referência:
//
// - a posição angular do último dente detectado;
// - o período medido entre os dois últimos dentes;
// - o tempo decorrido desde a última borda de subida do sensor CKP.
//
// Assume-se que a velocidade angular permanece aproximadamente constante
// durante o intervalo entre dois dentes consecutivos. Dessa forma, a posição
// angular pode ser estimada por interpolação linear.
//
// Exemplo para uma roda 60-2:
//
//            6°
// Dente ---------------- Dente
// 150°                  156°
//
// Se metade do tempo entre os dois dentes já transcorreu, estima-se que o
// virabrequim tenha percorrido aproximadamente metade da distância angular,
// resultando em:
//
// 150° + 3° = 153°
//
// A saída é fornecida em graus escalados (ANGLE_SCALE), permitindo aumentar a
// resolução angular sem utilizar números em ponto flutuante.
//
// Nesta primeira implementação, a interpolação é realizada por meio de uma
// divisão inteira. Caso necessário, esse cálculo poderá ser otimizado em
// versões futuras utilizando técnicas mais adequadas para FPGA, como
// multiplicação por fatores pré-calculados ou aritmética em ponto fixo.
//==============================================================================


module angle_interpolator #(
    parameter ANGLE_BITS = 16,
    parameter TIME_BITS = 32,
    parameter ANGLE_PER_TOOTH = 1092
)(
    input wire clk,
    input wire rst,
    input wire [15:0] tooth_number,
    input wire [TIME_BITS-1:0] tooth_period,
    input wire [TIME_BITS-1:0] time_since_tooth,
    input wire position_valid,
    
    output reg [ANGLE_BITS-1:0] interpolated_angle,
    output reg angle_valid
);

    always @(posedge clk) begin
        if (rst) begin
            interpolated_angle <= 0;
            angle_valid <= 0;
        end
        else begin
            angle_valid <= 0;

            if (position_valid) begin
                if (tooth_period != 0) begin
                    interpolated_angle <= (tooth_number * ANGLE_PER_TOOTH) + ((time_since_tooth * ANGLE_PER_TOOTH) / tooth_period);
                end
                else begin
                    interpolated_angle <= 0;
                end

                angle_valid <= 1;
            end
        end
    end
endmodule

project/sim/testbenches/engine_position/tb_angle_interpolator_math.v
`timescale 1ns/1ps

//==============================================================================
// Testbench: tb_angle_interpolator_math
//
// Objetivo:
//
// Validar a implementação matemática do módulo angle_interpolator.
//
// Este testbench aplica valores conhecidos de:
//
// - tooth_number;
// - tooth_period;
// - time_since_tooth;
//
// e verifica se a posição angular calculada corresponde ao valor esperado.
//
// O objetivo principal é validar:
//
// - a equação de interpolação linear;
// - a representação angular em ponto fixo;
// - a conversão entre tempo decorrido e deslocamento angular;
// - o comportamento nos pontos inicial, intermediário e final do intervalo
//   entre dois dentes.
//
// Este teste não simula a passagem real do tempo do motor. Os valores de
// time_since_tooth são aplicados diretamente para validar a matemática.
//
// Representação angular:
//
// 360° = 65536 unidades
//
// Para uma roda fônica 60-2:
//
// Δθ = 6°
//
// ANGLE_PER_TOOTH:
//
// 6 * 65536 / 360 = 1092
//
// Equação:
//
// θ = θ_base + (time_since_tooth * ANGLE_PER_TOOTH) / tooth_period
//
// Exemplo esperado:
//
// 0%   do período -> 0°
// 25%  do período -> 1,5°
// 50%  do período -> 3°
// 75%  do período -> 4,5°
// 100% do período -> 6°
//
//==============================================================================


module tb_angle_interpolator_math;

reg clk;
reg rst;
reg [15:0] tooth_number;
reg [31:0] tooth_period;
reg [31:0] time_since_tooth;
reg position_valid;

wire [15:0] interpolated_angle;
wire angle_valid;

real angle_deg;

angle_interpolator #(
    .ANGLE_BITS(16),
    .TIME_BITS(32),
    .ANGLE_PER_TOOTH(1092)
) dut (
    .clk(clk),
    .rst(rst),
    .tooth_number(tooth_number),
    .tooth_period(tooth_period),
    .time_since_tooth(time_since_tooth),
    .position_valid(position_valid),
    .interpolated_angle(interpolated_angle),
    .angle_valid(angle_valid)
);


always #10 clk = ~clk;


task test_angle;
    input [15:0] tooth;
    input [31:0] elapsed;

    begin
        tooth_number = tooth;
        time_since_tooth = elapsed;

        #20;

        angle_deg = (interpolated_angle * 360.0) / 65536.0;

        $display(
            "tooth=%0d | elapsed=%0d | raw=%0d | angle=%0.3f deg",
            tooth_number,
            time_since_tooth,
            interpolated_angle,
            angle_deg
        );
    end
endtask


initial begin

    $dumpfile("angle_interpolator_math.vcd");
    $dumpvars(0,tb_angle_interpolator_math);

    clk = 0;
    rst = 1;

    tooth_number = 0;
    tooth_period = 103448; // 500 RPM
    time_since_tooth = 0;
    position_valid = 0;


    #50;

    rst = 0;
    position_valid = 1;


    // Teste de linearidade do primeiro dente
    test_angle(0,0);
    test_angle(0,25862);
    test_angle(0,51724);
    test_angle(0,77586);
    test_angle(0,103448);


    // Teste com deslocamento angular da roda
    test_angle(10,0);
    test_angle(10,51724);


    // Teste próximo ao final da roda
    test_angle(57,0);
    test_angle(57,103448);


    position_valid = 0;

    #100;

    $finish;

end


endmodule

angle_interpolator_math.vcd
$date
	Tue Jul 28 21:01:46 2026
$end
$version
	Icarus Verilog
$end
$timescale
	1ps
$end
$scope module tb_angle_interpolator_math $end
$var wire 16 ! interpolated_angle [15:0] $end
$var wire 1 " angle_valid $end
$var reg 1 # clk $end
$var reg 1 $ position_valid $end
$var reg 1 % rst $end
$var reg 32 & time_since_tooth [31:0] $end
$var reg 16 ' tooth_number [15:0] $end
$var reg 32 ( tooth_period [31:0] $end
$var real 1 ) angle_deg $end
$scope module dut $end
$var wire 1 # clk $end
$var wire 1 $ position_valid $end
$var wire 1 % rst $end
$var wire 32 * time_since_tooth [31:0] $end
$var wire 16 + tooth_number [15:0] $end
$var wire 32 , tooth_period [31:0] $end
$var parameter 32 - ANGLE_BITS $end
$var parameter 32 . ANGLE_PER_TOOTH $end
$var parameter 32 / TIME_BITS $end
$var reg 1 " angle_valid $end
$var reg 16 0 interpolated_angle [15:0] $end
$upscope $end
$scope task test_angle $end
$var reg 32 1 elapsed [31:0] $end
$var reg 16 2 tooth [15:0] $end
$upscope $end
$upscope $end
$enddefinitions $end
$comment Show the parameter values. $end
$dumpall
b100000 /
b10001000100 .
b10000 -
$end
#0
$dumpvars
bx 2
bx 1
bx 0
b11001010000011000 ,
b0 +
b0 *
r0 )
b11001010000011000 (
b0 '
b0 &
1%
0$
0#
x"
bx !
$end
#10000
0"
b0 !
b0 0
1#
#20000
0#
#30000
1#
#40000
0#
#50000
1"
1#
b0 1
b0 2
1$
0%
#60000
0#
#70000
b100010001 !
b100010001 0
1"
1#
b110010100000110 &
b110010100000110 *
b110010100000110 1
#80000
0#
#90000
b1000100010 !
b1000100010 0
1"
1#
b1100101000001100 &
b1100101000001100 *
b1100101000001100 1
r1.4996337890625 )
#100000
0#
#110000
b1100110011 !
b1100110011 0
1"
1#
b10010111100010010 &
b10010111100010010 *
b10010111100010010 1
r2.999267578125 )
#120000
0#
#130000
b10001000100 !
b10001000100 0
1"
1#
b11001010000011000 &
b11001010000011000 *
b11001010000011000 1
r4.4989013671875 )
#140000
0#
#150000
b10101010101000 !
b10101010101000 0
1"
1#
b0 &
b0 *
b1010 '
b1010 +
b0 1
b1010 2
r5.99853515625 )
#160000
0#
#170000
b10110011001010 !
b10110011001010 0
1"
1#
b1100101000001100 &
b1100101000001100 *
b1100101000001100 1
r59.9853515625 )
#180000
0#
#190000
b1111001100100100 !
b1111001100100100 0
1"
1#
b0 &
b0 *
b111001 '
b111001 +
b0 1
b111001 2
r62.984619140625 )
#200000
0#
#210000
b1111011101101000 !
b1111011101101000 0
1"
1#
b11001010000011000 &
b11001010000011000 *
b11001010000011000 1
r341.91650390625 )
#220000
0#
#230000
0"
1#
0$
r347.9150390625 )
