project/rtl/crankshaft/angle_interpolator.v
//==============================================================================
// Módulo: angle_interpolator
//
// Descrição:
// Estima continuamente a posição angular do virabrequim entre dois dentes
// consecutivos da roda fônica.
//
// O módulo utiliza como referência:
//
// - a posição angular do último dente detectado;
// - o período medido entre os dois últimos dentes;
// - o tempo decorrido desde a última borda de subida do sensor CKP.
//
// Assume-se que a velocidade angular permanece aproximadamente constante
// durante o intervalo entre dois dentes consecutivos. Dessa forma, a posição
// angular pode ser estimada por interpolação linear.
//
// Exemplo para uma roda 60-2:
//
//            6°
// Dente ---------------- Dente
// 150°                  156°
//
// Se metade do tempo entre os dois dentes já transcorreu, estima-se que o
// virabrequim tenha percorrido aproximadamente metade da distância angular,
// resultando em:
//
// 150° + 3° = 153°
//
// A saída é fornecida em graus escalados (ANGLE_SCALE), permitindo aumentar a
// resolução angular sem utilizar números em ponto flutuante.
//
// Nesta primeira implementação, a interpolação é realizada por meio de uma
// divisão inteira. Caso necessário, esse cálculo poderá ser otimizado em
// versões futuras utilizando técnicas mais adequadas para FPGA, como
// multiplicação por fatores pré-calculados ou aritmética em ponto fixo.
//==============================================================================

// module angle_interpolator #(
//     parameter TOTAL_TEETH = 60,
//     parameter ANGLE_SCALE = 10,

//     localparam ANGLE_PER_TOOTH = (360 * ANGLE_SCALE) / TOTAL_TEETH,
//     localparam ANGLE_WIDTH = $clog2(360 * ANGLE_SCALE)
// )(
//     input wire clk,
//     input wire rst,

//     input wire tooth_rise,

//     input wire [31:0] tooth_period,
//     input wire tooth_period_valid,

//     input wire [ANGLE_WIDTH-1:0] crankshaft_angle,
//     input wire position_valid,

//     output reg [ANGLE_WIDTH-1:0] interpolated_angle,
//     output reg interpolated_valid
// );

//     reg [31:0] elapsed_time;
//     reg [31:0] last_tooth_period;

//     reg [ANGLE_WIDTH:0] base_angle;
//     reg [ANGLE_WIDTH:0] increment;
//     reg [ANGLE_WIDTH:0] angle_temp;

//     always @(posedge clk) begin
//         if (rst) begin
//             elapsed_time <= 0;
//             last_tooth_period <= 0;
//             interpolated_angle <= 0;
//             interpolated_valid <= 0;

//         end
//         else begin

//             /*
//              * Antes do sincronismo ser estabelecido, a posição
//              * angular não é conhecida e, portanto, não é possível
//              * realizar a interpolação.
//              */
//             if (!position_valid) begin
//                 elapsed_time <= 0;
//                 interpolated_angle <= 0;
//                 interpolated_valid <= 0;

//             end
//             else begin

//                 interpolated_valid <= 1;

//                 /*
//                  * Armazena o último período válido medido entre
//                  * dois dentes consecutivos da roda fônica.
//                  */
//                 if (tooth_period_valid) begin
//                     last_tooth_period <= tooth_period;
//                 end

//                 /*
//                  * Atualiza o tempo decorrido desde o último dente.
//                  */
//                 if (tooth_rise) begin
//                     elapsed_time <= 0;
//                 end
//                 else begin
//                     elapsed_time <= elapsed_time + 1;
//                 end

//                 /*
//                  * Calcula continuamente a posição angular estimada
//                  * entre dois dentes consecutivos.
//                  */
//                 base_angle = crankshaft_angle * ANGLE_SCALE;

//                 if (last_tooth_period != 0) begin
//                     increment =
//                         (elapsed_time * ANGLE_PER_TOOTH) /
//                         last_tooth_period;
//                 end
//                 else begin
//                     increment = 0;
//                 end

//                 angle_temp = base_angle + increment;

//                 /*
//                  * Durante a transição entre o último dente físico
//                  * (354°) e a referência da próxima volta (0°),
//                  * permite que a interpolação alcance 360° antes
//                  * de reiniciar em zero.
//                  */
//                 if ((crankshaft_angle == 0) && (increment != 0)) begin
//                     interpolated_angle <= (360 * ANGLE_SCALE) + increment;
//                 end
//                 else begin
//                     interpolated_angle <= angle_temp[ANGLE_WIDTH-1:0];
//                 end

//             end
//         end
//     end
// endmodule


module angle_interpolator #(
    parameter ANGLE_BITS = 16,
    parameter TIME_BITS = 32,
    parameter TOOTH_ANGLE = 6
)(
    input wire clk,
    input wire rst,
    input wire [15:0] tooth_number,
    input wire [TIME_BITS-1:0] tooth_period,
    input wire [TIME_BITS-1:0] time_since_tooth,
    input wire position_valid,
    
    output reg [ANGLE_BITS-1:0] interpolated_angle,
    output reg angle_valid
);

    reg [31:0] angle_base;
    reg [31:0] interpolation;

    always @(posedge clk) begin
        if (rst) begin
            interpolated_angle <= 0;
            angle_valid <= 0;
        end
        else begin
            angle_valid <= 0;
            if (position_valid) begin
                angle_base = tooth_number * TOOTH_ANGLE;
                if (tooth_period != 0) begin
                    interpolation = (time_since_tooth * TOOTH_ANGLE) / tooth_period;
                end
                else begin
                    interpolation = 0;
                end

                interpolated_angle <= angle_base + interpolation;
                angle_valid <= 1;
            end
        end
    end
endmodule

project/sim/testbenches/tb_angle_interpolator.v
`timescale 1ns/1ps

module tb_angle_interpolator;

reg clk;
reg rst;
reg [15:0] tooth_number;
reg [31:0] tooth_period;
reg [31:0] time_since_tooth;
reg position_valid;

wire [15:0] interpolated_angle;
wire angle_valid;

angle_interpolator #(
    .ANGLE_BITS(16),
    .TIME_BITS(32),
    .TOOTH_ANGLE(6)
) dut (
    .clk(clk),
    .rst(rst),
    .tooth_number(tooth_number),
    .tooth_period(tooth_period),
    .time_since_tooth(time_since_tooth),
    .position_valid(position_valid),
    .interpolated_angle(interpolated_angle),
    .angle_valid(angle_valid)
);

always #10 clk = ~clk;

integer i;

initial begin
    $dumpfile("angle_interpolator.vcd");
    $dumpvars(0,tb_angle_interpolator);

    clk = 0;
    rst = 1;
    tooth_number = 0;
    tooth_period = 1000;
    time_since_tooth = 0;
    position_valid = 0;

    #50;

    rst = 0;
    position_valid = 1;

    for(i = 0; i < 58; i = i + 1)
    begin
        tooth_number = i;

        time_since_tooth = 0;
        #20;

        time_since_tooth = 250;
        #20;

        time_since_tooth = 500;
        #20;

        time_since_tooth = 750;
        #20;
    end

    position_valid = 0;

    #100;

    $finish;
end

always @(posedge clk)
begin
    if(angle_valid)
    begin
        $display(
            "time=%0t | tooth=%0d | elapsed=%0d | angle=%0d",
            $time,
            tooth_number,
            time_since_tooth,
            interpolated_angle
        );
    end
end

endmodule

angle_interpolator.vcd
$date
	Thu Jul 23 20:57:55 2026
$end
$version
	Icarus Verilog
$end
$timescale
	1ps
$end
$scope module tb_angle_interpolator $end
$var wire 16 ! interpolated_angle [15:0] $end
$var wire 1 " angle_valid $end
$var reg 1 # clk $end
$var reg 1 $ position_valid $end
$var reg 1 % rst $end
$var reg 32 & time_since_tooth [31:0] $end
$var reg 16 ' tooth_number [15:0] $end
$var reg 32 ( tooth_period [31:0] $end
$var integer 32 ) i [31:0] $end
$scope module dut $end
$var wire 1 # clk $end
$var wire 1 $ position_valid $end
$var wire 1 % rst $end
$var wire 32 * time_since_tooth [31:0] $end
$var wire 16 + tooth_number [15:0] $end
$var wire 32 , tooth_period [31:0] $end
$var reg 32 - angle_base [31:0] $end
$var reg 1 " angle_valid $end
$var reg 16 . interpolated_angle [15:0] $end
$var reg 32 / interpolation [31:0] $end
$upscope $end
$upscope $end
$enddefinitions $end
#0
$dumpvars
bx /
bx .
bx -
b1111101000 ,
b0 +
b0 *
bx )
b1111101000 (
b0 '
b0 &
1%
0$
0#
x"
bx !
$end
#10000
0"
b0 !
b0 .
1#
#20000
0#
#30000
1#
#40000
0#
#50000
1"
b0 /
b0 -
1#
b0 )
1$
0%
#60000
0#
#70000
b1 !
b1 .
1"
b1 /
1#
b11111010 &
b11111010 *
#80000
0#
#90000
b11 !
b11 .
1"
b11 /
1#
b111110100 &
b111110100 *
#100000
0#
#110000
b100 !
b100 .
1"
b100 /
1#
b1011101110 &
b1011101110 *
#120000
0#
#130000
b110 !
b110 .
1"
b0 /
b110 -
1#
b0 &
b0 *
b1 '
b1 +
b1 )
#140000
0#
#150000
b111 !
b111 .
1"
b1 /
1#
b11111010 &
b11111010 *
#160000
0#
#170000
b1001 !
b1001 .
1"
b11 /
1#
b111110100 &
b111110100 *
#180000
0#
#190000
b1010 !
b1010 .
1"
b100 /
1#
b1011101110 &
b1011101110 *
#200000
0#
#210000
b1100 !
b1100 .
1"
b0 /
b1100 -
1#
b0 &
b0 *
b10 '
b10 +
b10 )
#220000
0#
#230000
b1101 !
b1101 .
1"
b1 /
1#
b11111010 &
b11111010 *
#240000
0#
#250000
b1111 !
b1111 .
1"
b11 /
1#
b111110100 &
b111110100 *
#260000
0#
#270000
b10000 !
b10000 .
1"
b100 /
1#
b1011101110 &
b1011101110 *
#280000
0#
#290000
b10010 !
b10010 .
1"
b0 /
b10010 -
1#
b0 &
b0 *
b11 '
b11 +
b11 )
#300000
0#
#310000
b10011 !
b10011 .
1"
b1 /
1#
b11111010 &
b11111010 *
#320000
0#
#330000
b10101 !
b10101 .
1"
b11 /
1#
b111110100 &
b111110100 *
#340000
0#
#350000
b10110 !
b10110 .
1"
b100 /
1#
b1011101110 &
b1011101110 *
#360000
0#
#370000
b11000 !
b11000 .
1"
b0 /
b11000 -
1#
b0 &
b0 *
b100 '
b100 +
b100 )
#380000
0#
#390000
b11001 !
b11001 .
1"
b1 /
1#
b11111010 &
b11111010 *
#400000
0#
#410000
b11011 !
b11011 .
1"
b11 /
1#
b111110100 &
b111110100 *
#420000
0#
#430000
b11100 !
b11100 .
1"
b100 /
1#
b1011101110 &
b1011101110 *
#440000
0#
#450000
b11110 !
b11110 .
1"
b0 /
b11110 -
1#
b0 &
b0 *
b101 '
b101 +
b101 )
#460000
0#
#470000
b11111 !
b11111 .
1"
b1 /
1#
b11111010 &
b11111010 *
#480000
0#
#490000
b100001 !
b100001 .
1"
b11 /
1#
b111110100 &
b111110100 *
#500000
0#
#510000
b100010 !
b100010 .
1"
b100 /
1#
b1011101110 &
b1011101110 *
#520000
0#
#530000
b100100 !
b100100 .
1"
b0 /
b100100 -
1#
b0 &
b0 *
b110 '
b110 +
b110 )
#540000
0#
#550000
b100101 !
b100101 .
1"
b1 /
1#
b11111010 &
b11111010 *
#560000
0#
#570000
b100111 !
b100111 .
1"
b11 /
1#
b111110100 &
b111110100 *
#580000
0#
#590000
b101000 !
b101000 .
1"
b100 /
1#
b1011101110 &
b1011101110 *
#600000
0#
#610000
b101010 !
b101010 .
1"
b0 /
b101010 -
1#
b0 &
b0 *
b111 '
b111 +
b111 )
#620000
0#
#630000
b101011 !
b101011 .
1"
b1 /
1#
b11111010 &
b11111010 *
#640000
0#
#650000
b101101 !
b101101 .
1"
b11 /
1#
b111110100 &
b111110100 *
#660000
0#
#670000
b101110 !
b101110 .
1"
b100 /
1#
b1011101110 &
b1011101110 *
#680000
0#
#690000
b110000 !
b110000 .
1"
b0 /
b110000 -
1#
b0 &
b0 *
b1000 '
b1000 +
b1000 )
#700000
0#
#710000
b110001 !
b110001 .
1"
b1 /
1#
b11111010 &
b11111010 *
#720000
0#
#730000
b110011 !
b110011 .
1"
b11 /
1#
b111110100 &
b111110100 *
#740000
0#
#750000
b110100 !
b110100 .
1"
b100 /
1#
b1011101110 &
b1011101110 *
#760000
0#
#770000
b110110 !
b110110 .
1"
b0 /
b110110 -
1#
b0 &
b0 *
b1001 '
b1001 +
b1001 )
#780000
0#
#790000
b110111 !
b110111 .
1"
b1 /
1#
b11111010 &
b11111010 *
#800000
0#
#810000
b111001 !
b111001 .
1"
b11 /
1#
b111110100 &
b111110100 *
#820000
0#
#830000
b111010 !
b111010 .
1"
b100 /
1#
b1011101110 &
b1011101110 *
#840000
0#
#850000
b111100 !
b111100 .
1"
b0 /
b111100 -
1#
b0 &
b0 *
b1010 '
b1010 +
b1010 )
#860000
0#
#870000
b111101 !
b111101 .
1"
b1 /
1#
b11111010 &
b11111010 *
#880000
0#
#890000
b111111 !
b111111 .
1"
b11 /
1#
b111110100 &
b111110100 *
#900000
0#
#910000
b1000000 !
b1000000 .
1"
b100 /
1#
b1011101110 &
b1011101110 *
#920000
0#
#930000
b1000010 !
b1000010 .
1"
b0 /
b1000010 -
1#
b0 &
b0 *
b1011 '
b1011 +
b1011 )
#940000
0#
#950000
b1000011 !
b1000011 .
1"
b1 /
1#
b11111010 &
b11111010 *
#960000
0#
#970000
b1000101 !
b1000101 .
1"
b11 /
1#
b111110100 &
b111110100 *
#980000
0#
#990000
b1000110 !
b1000110 .
1"
b100 /
1#
b1011101110 &
b1011101110 *
#1000000
0#
#1010000
b1001000 !
b1001000 .
1"
b0 /
b1001000 -
1#
b0 &
b0 *
b1100 '
b1100 +
b1100 )
#1020000
0#
#1030000
b1001001 !
b1001001 .
1"
b1 /
1#
b11111010 &
b11111010 *
#1040000
0#
#1050000
b1001011 !
b1001011 .
1"
b11 /
1#
b111110100 &
b111110100 *
#1060000
0#
#1070000
b1001100 !
b1001100 .
1"
b100 /
1#
b1011101110 &
b1011101110 *
#1080000
0#
#1090000
b1001110 !
b1001110 .
1"
b0 /
b1001110 -
1#
b0 &
b0 *
b1101 '
b1101 +
b1101 )
#1100000
0#
#1110000
b1001111 !
b1001111 .
1"
b1 /
1#
b11111010 &
b11111010 *
#1120000
0#
#1130000
b1010001 !
b1010001 .
1"
b11 /
1#
b111110100 &
b111110100 *
#1140000
0#
#1150000
b1010010 !
b1010010 .
1"
b100 /
1#
b1011101110 &
b1011101110 *
#1160000
0#
#1170000
b1010100 !
b1010100 .
1"
b0 /
b1010100 -
1#
b0 &
b0 *
b1110 '
b1110 +
b1110 )
#1180000
0#
#1190000
b1010101 !
b1010101 .
1"
b1 /
1#
b11111010 &
b11111010 *
#1200000
0#
#1210000
b1010111 !
b1010111 .
1"
b11 /
1#
b111110100 &
b111110100 *
#1220000
0#
#1230000
b1011000 !
b1011000 .
1"
b100 /
1#
b1011101110 &
b1011101110 *
#1240000
0#
#1250000
b1011010 !
b1011010 .
1"
b0 /
b1011010 -
1#
b0 &
b0 *
b1111 '
b1111 +
b1111 )
#1260000
0#
#1270000
b1011011 !
b1011011 .
1"
b1 /
1#
b11111010 &
b11111010 *
#1280000
0#
#1290000
b1011101 !
b1011101 .
1"
b11 /
1#
b111110100 &
b111110100 *
#1300000
0#
#1310000
b1011110 !
b1011110 .
1"
b100 /
1#
b1011101110 &
b1011101110 *
#1320000
0#
#1330000
b1100000 !
b1100000 .
1"
b0 /
b1100000 -
1#
b0 &
b0 *
b10000 '
b10000 +
b10000 )
#1340000
0#
#1350000
b1100001 !
b1100001 .
1"
b1 /
1#
b11111010 &
b11111010 *
#1360000
0#
#1370000
b1100011 !
b1100011 .
1"
b11 /
1#
b111110100 &
b111110100 *
#1380000
0#
#1390000
b1100100 !
b1100100 .
1"
b100 /
1#
b1011101110 &
b1011101110 *
#1400000
0#
#1410000
b1100110 !
b1100110 .
1"
b0 /
b1100110 -
1#
b0 &
b0 *
b10001 '
b10001 +
b10001 )
#1420000
0#
#1430000
b1100111 !
b1100111 .
1"
b1 /
1#
b11111010 &
b11111010 *
#1440000
0#
#1450000
b1101001 !
b1101001 .
1"
b11 /
1#
b111110100 &
b111110100 *
#1460000
0#
#1470000
b1101010 !
b1101010 .
1"
b100 /
1#
b1011101110 &
b1011101110 *
#1480000
0#
#1490000
b1101100 !
b1101100 .
1"
b0 /
b1101100 -
1#
b0 &
b0 *
b10010 '
b10010 +
b10010 )
#1500000
0#
#1510000
b1101101 !
b1101101 .
1"
b1 /
1#
b11111010 &
b11111010 *
#1520000
0#
#1530000
b1101111 !
b1101111 .
1"
b11 /
1#
b111110100 &
b111110100 *
#1540000
0#
#1550000
b1110000 !
b1110000 .
1"
b100 /
1#
b1011101110 &
b1011101110 *
#1560000
0#
#1570000
b1110010 !
b1110010 .
1"
b0 /
b1110010 -
1#
b0 &
b0 *
b10011 '
b10011 +
b10011 )
#1580000
0#
#1590000
b1110011 !
b1110011 .
1"
b1 /
1#
b11111010 &
b11111010 *
#1600000
0#
#1610000
b1110101 !
b1110101 .
1"
b11 /
1#
b111110100 &
b111110100 *
#1620000
0#
#1630000
b1110110 !
b1110110 .
1"
b100 /
1#
b1011101110 &
b1011101110 *
#1640000
0#
#1650000
b1111000 !
b1111000 .
1"
b0 /
b1111000 -
1#
b0 &
b0 *
b10100 '
b10100 +
b10100 )
#1660000
0#
#1670000
b1111001 !
b1111001 .
1"
b1 /
1#
b11111010 &
b11111010 *
#1680000
0#
#1690000
b1111011 !
b1111011 .
1"
b11 /
1#
b111110100 &
b111110100 *
#1700000
0#
#1710000
b1111100 !
b1111100 .
1"
b100 /
1#
b1011101110 &
b1011101110 *
#1720000
0#
#1730000
b1111110 !
b1111110 .
1"
b0 /
b1111110 -
1#
b0 &
b0 *
b10101 '
b10101 +
b10101 )
#1740000
0#
#1750000
b1111111 !
b1111111 .
1"
b1 /
1#
b11111010 &
b11111010 *
#1760000
0#
#1770000
b10000001 !
b10000001 .
1"
b11 /
1#
b111110100 &
b111110100 *
#1780000
0#
#1790000
b10000010 !
b10000010 .
1"
b100 /
1#
b1011101110 &
b1011101110 *
#1800000
0#
#1810000
b10000100 !
b10000100 .
1"
b0 /
b10000100 -
1#
b0 &
b0 *
b10110 '
b10110 +
b10110 )
#1820000
0#
#1830000
b10000101 !
b10000101 .
1"
b1 /
1#
b11111010 &
b11111010 *
#1840000
0#
#1850000
b10000111 !
b10000111 .
1"
b11 /
1#
b111110100 &
b111110100 *
#1860000
0#
#1870000
b10001000 !
b10001000 .
1"
b100 /
1#
b1011101110 &
b1011101110 *
#1880000
0#
#1890000
b10001010 !
b10001010 .
1"
b0 /
b10001010 -
1#
b0 &
b0 *
b10111 '
b10111 +
b10111 )
#1900000
0#
#1910000
b10001011 !
b10001011 .
1"
b1 /
1#
b11111010 &
b11111010 *
#1920000
0#
#1930000
b10001101 !
b10001101 .
1"
b11 /
1#
b111110100 &
b111110100 *
#1940000
0#
#1950000
b10001110 !
b10001110 .
1"
b100 /
1#
b1011101110 &
b1011101110 *
#1960000
0#
#1970000
b10010000 !
b10010000 .
1"
b0 /
b10010000 -
1#
b0 &
b0 *
b11000 '
b11000 +
b11000 )
#1980000
0#
#1990000
b10010001 !
b10010001 .
1"
b1 /
1#
b11111010 &
b11111010 *
#2000000
0#
#2010000
b10010011 !
b10010011 .
1"
b11 /
1#
b111110100 &
b111110100 *
#2020000
0#
#2030000
b10010100 !
b10010100 .
1"
b100 /
1#
b1011101110 &
b1011101110 *
#2040000
0#
#2050000
b10010110 !
b10010110 .
1"
b0 /
b10010110 -
1#
b0 &
b0 *
b11001 '
b11001 +
b11001 )
#2060000
0#
#2070000
b10010111 !
b10010111 .
1"
b1 /
1#
b11111010 &
b11111010 *
#2080000
0#
#2090000
b10011001 !
b10011001 .
1"
b11 /
1#
b111110100 &
b111110100 *
#2100000
0#
#2110000
b10011010 !
b10011010 .
1"
b100 /
1#
b1011101110 &
b1011101110 *
#2120000
0#
#2130000
b10011100 !
b10011100 .
1"
b0 /
b10011100 -
1#
b0 &
b0 *
b11010 '
b11010 +
b11010 )
#2140000
0#
#2150000
b10011101 !
b10011101 .
1"
b1 /
1#
b11111010 &
b11111010 *
#2160000
0#
#2170000
b10011111 !
b10011111 .
1"
b11 /
1#
b111110100 &
b111110100 *
#2180000
0#
#2190000
b10100000 !
b10100000 .
1"
b100 /
1#
b1011101110 &
b1011101110 *
#2200000
0#
#2210000
b10100010 !
b10100010 .
1"
b0 /
b10100010 -
1#
b0 &
b0 *
b11011 '
b11011 +
b11011 )
#2220000
0#
#2230000
b10100011 !
b10100011 .
1"
b1 /
1#
b11111010 &
b11111010 *
#2240000
0#
#2250000
b10100101 !
b10100101 .
1"
b11 /
1#
b111110100 &
b111110100 *
#2260000
0#
#2270000
b10100110 !
b10100110 .
1"
b100 /
1#
b1011101110 &
b1011101110 *
#2280000
0#
#2290000
b10101000 !
b10101000 .
1"
b0 /
b10101000 -
1#
b0 &
b0 *
b11100 '
b11100 +
b11100 )
#2300000
0#
#2310000
b10101001 !
b10101001 .
1"
b1 /
1#
b11111010 &
b11111010 *
#2320000
0#
#2330000
b10101011 !
b10101011 .
1"
b11 /
1#
b111110100 &
b111110100 *
#2340000
0#
#2350000
b10101100 !
b10101100 .
1"
b100 /
1#
b1011101110 &
b1011101110 *
#2360000
0#
#2370000
b10101110 !
b10101110 .
1"
b0 /
b10101110 -
1#
b0 &
b0 *
b11101 '
b11101 +
b11101 )
#2380000
0#
#2390000
b10101111 !
b10101111 .
1"
b1 /
1#
b11111010 &
b11111010 *
#2400000
0#
#2410000
b10110001 !
b10110001 .
1"
b11 /
1#
b111110100 &
b111110100 *
#2420000
0#
#2430000
b10110010 !
b10110010 .
1"
b100 /
1#
b1011101110 &
b1011101110 *
#2440000
0#
#2450000
b10110100 !
b10110100 .
1"
b0 /
b10110100 -
1#
b0 &
b0 *
b11110 '
b11110 +
b11110 )
#2460000
0#
#2470000
b10110101 !
b10110101 .
1"
b1 /
1#
b11111010 &
b11111010 *
#2480000
0#
#2490000
b10110111 !
b10110111 .
1"
b11 /
1#
b111110100 &
b111110100 *
#2500000
0#
#2510000
b10111000 !
b10111000 .
1"
b100 /
1#
b1011101110 &
b1011101110 *
#2520000
0#
#2530000
b10111010 !
b10111010 .
1"
b0 /
b10111010 -
1#
b0 &
b0 *
b11111 '
b11111 +
b11111 )
#2540000
0#
#2550000
b10111011 !
b10111011 .
1"
b1 /
1#
b11111010 &
b11111010 *
#2560000
0#
#2570000
b10111101 !
b10111101 .
1"
b11 /
1#
b111110100 &
b111110100 *
#2580000
0#
#2590000
b10111110 !
b10111110 .
1"
b100 /
1#
b1011101110 &
b1011101110 *
#2600000
0#
#2610000
b11000000 !
b11000000 .
1"
b0 /
b11000000 -
1#
b0 &
b0 *
b100000 '
b100000 +
b100000 )
#2620000
0#
#2630000
b11000001 !
b11000001 .
1"
b1 /
1#
b11111010 &
b11111010 *
#2640000
0#
#2650000
b11000011 !
b11000011 .
1"
b11 /
1#
b111110100 &
b111110100 *
#2660000
0#
#2670000
b11000100 !
b11000100 .
1"
b100 /
1#
b1011101110 &
b1011101110 *
#2680000
0#
#2690000
b11000110 !
b11000110 .
1"
b0 /
b11000110 -
1#
b0 &
b0 *
b100001 '
b100001 +
b100001 )
#2700000
0#
#2710000
b11000111 !
b11000111 .
1"
b1 /
1#
b11111010 &
b11111010 *
#2720000
0#
#2730000
b11001001 !
b11001001 .
1"
b11 /
1#
b111110100 &
b111110100 *
#2740000
0#
#2750000
b11001010 !
b11001010 .
1"
b100 /
1#
b1011101110 &
b1011101110 *
#2760000
0#
#2770000
b11001100 !
b11001100 .
1"
b0 /
b11001100 -
1#
b0 &
b0 *
b100010 '
b100010 +
b100010 )
#2780000
0#
#2790000
b11001101 !
b11001101 .
1"
b1 /
1#
b11111010 &
b11111010 *
#2800000
0#
#2810000
b11001111 !
b11001111 .
1"
b11 /
1#
b111110100 &
b111110100 *
#2820000
0#
#2830000
b11010000 !
b11010000 .
1"
b100 /
1#
b1011101110 &
b1011101110 *
#2840000
0#
#2850000
b11010010 !
b11010010 .
1"
b0 /
b11010010 -
1#
b0 &
b0 *
b100011 '
b100011 +
b100011 )
#2860000
0#
#2870000
b11010011 !
b11010011 .
1"
b1 /
1#
b11111010 &
b11111010 *
#2880000
0#
#2890000
b11010101 !
b11010101 .
1"
b11 /
1#
b111110100 &
b111110100 *
#2900000
0#
#2910000
b11010110 !
b11010110 .
1"
b100 /
1#
b1011101110 &
b1011101110 *
#2920000
0#
#2930000
b11011000 !
b11011000 .
1"
b0 /
b11011000 -
1#
b0 &
b0 *
b100100 '
b100100 +
b100100 )
#2940000
0#
#2950000
b11011001 !
b11011001 .
1"
b1 /
1#
b11111010 &
b11111010 *
#2960000
0#
#2970000
b11011011 !
b11011011 .
1"
b11 /
1#
b111110100 &
b111110100 *
#2980000
0#
#2990000
b11011100 !
b11011100 .
1"
b100 /
1#
b1011101110 &
b1011101110 *
#3000000
0#
#3010000
b11011110 !
b11011110 .
1"
b0 /
b11011110 -
1#
b0 &
b0 *
b100101 '
b100101 +
b100101 )
#3020000
0#
#3030000
b11011111 !
b11011111 .
1"
b1 /
1#
b11111010 &
b11111010 *
#3040000
0#
#3050000
b11100001 !
b11100001 .
1"
b11 /
1#
b111110100 &
b111110100 *
#3060000
0#
#3070000
b11100010 !
b11100010 .
1"
b100 /
1#
b1011101110 &
b1011101110 *
#3080000
0#
#3090000
b11100100 !
b11100100 .
1"
b0 /
b11100100 -
1#
b0 &
b0 *
b100110 '
b100110 +
b100110 )
#3100000
0#
#3110000
b11100101 !
b11100101 .
1"
b1 /
1#
b11111010 &
b11111010 *
#3120000
0#
#3130000
b11100111 !
b11100111 .
1"
b11 /
1#
b111110100 &
b111110100 *
#3140000
0#
#3150000
b11101000 !
b11101000 .
1"
b100 /
1#
b1011101110 &
b1011101110 *
#3160000
0#
#3170000
b11101010 !
b11101010 .
1"
b0 /
b11101010 -
1#
b0 &
b0 *
b100111 '
b100111 +
b100111 )
#3180000
0#
#3190000
b11101011 !
b11101011 .
1"
b1 /
1#
b11111010 &
b11111010 *
#3200000
0#
#3210000
b11101101 !
b11101101 .
1"
b11 /
1#
b111110100 &
b111110100 *
#3220000
0#
#3230000
b11101110 !
b11101110 .
1"
b100 /
1#
b1011101110 &
b1011101110 *
#3240000
0#
#3250000
b11110000 !
b11110000 .
1"
b0 /
b11110000 -
1#
b0 &
b0 *
b101000 '
b101000 +
b101000 )
#3260000
0#
#3270000
b11110001 !
b11110001 .
1"
b1 /
1#
b11111010 &
b11111010 *
#3280000
0#
#3290000
b11110011 !
b11110011 .
1"
b11 /
1#
b111110100 &
b111110100 *
#3300000
0#
#3310000
b11110100 !
b11110100 .
1"
b100 /
1#
b1011101110 &
b1011101110 *
#3320000
0#
#3330000
b11110110 !
b11110110 .
1"
b0 /
b11110110 -
1#
b0 &
b0 *
b101001 '
b101001 +
b101001 )
#3340000
0#
#3350000
b11110111 !
b11110111 .
1"
b1 /
1#
b11111010 &
b11111010 *
#3360000
0#
#3370000
b11111001 !
b11111001 .
1"
b11 /
1#
b111110100 &
b111110100 *
#3380000
0#
#3390000
b11111010 !
b11111010 .
1"
b100 /
1#
b1011101110 &
b1011101110 *
#3400000
0#
#3410000
b11111100 !
b11111100 .
1"
b0 /
b11111100 -
1#
b0 &
b0 *
b101010 '
b101010 +
b101010 )
#3420000
0#
#3430000
b11111101 !
b11111101 .
1"
b1 /
1#
b11111010 &
b11111010 *
#3440000
0#
#3450000
b11111111 !
b11111111 .
1"
b11 /
1#
b111110100 &
b111110100 *
#3460000
0#
#3470000
b100000000 !
b100000000 .
1"
b100 /
1#
b1011101110 &
b1011101110 *
#3480000
0#
#3490000
b100000010 !
b100000010 .
1"
b0 /
b100000010 -
1#
b0 &
b0 *
b101011 '
b101011 +
b101011 )
#3500000
0#
#3510000
b100000011 !
b100000011 .
1"
b1 /
1#
b11111010 &
b11111010 *
#3520000
0#
#3530000
b100000101 !
b100000101 .
1"
b11 /
1#
b111110100 &
b111110100 *
#3540000
0#
#3550000
b100000110 !
b100000110 .
1"
b100 /
1#
b1011101110 &
b1011101110 *
#3560000
0#
#3570000
b100001000 !
b100001000 .
1"
b0 /
b100001000 -
1#
b0 &
b0 *
b101100 '
b101100 +
b101100 )
#3580000
0#
#3590000
b100001001 !
b100001001 .
1"
b1 /
1#
b11111010 &
b11111010 *
#3600000
0#
#3610000
b100001011 !
b100001011 .
1"
b11 /
1#
b111110100 &
b111110100 *
#3620000
0#
#3630000
b100001100 !
b100001100 .
1"
b100 /
1#
b1011101110 &
b1011101110 *
#3640000
0#
#3650000
b100001110 !
b100001110 .
1"
b0 /
b100001110 -
1#
b0 &
b0 *
b101101 '
b101101 +
b101101 )
#3660000
0#
#3670000
b100001111 !
b100001111 .
1"
b1 /
1#
b11111010 &
b11111010 *
#3680000
0#
#3690000
b100010001 !
b100010001 .
1"
b11 /
1#
b111110100 &
b111110100 *
#3700000
0#
#3710000
b100010010 !
b100010010 .
1"
b100 /
1#
b1011101110 &
b1011101110 *
#3720000
0#
#3730000
b100010100 !
b100010100 .
1"
b0 /
b100010100 -
1#
b0 &
b0 *
b101110 '
b101110 +
b101110 )
#3740000
0#
#3750000
b100010101 !
b100010101 .
1"
b1 /
1#
b11111010 &
b11111010 *
#3760000
0#
#3770000
b100010111 !
b100010111 .
1"
b11 /
1#
b111110100 &
b111110100 *
#3780000
0#
#3790000
b100011000 !
b100011000 .
1"
b100 /
1#
b1011101110 &
b1011101110 *
#3800000
0#
#3810000
b100011010 !
b100011010 .
1"
b0 /
b100011010 -
1#
b0 &
b0 *
b101111 '
b101111 +
b101111 )
#3820000
0#
#3830000
b100011011 !
b100011011 .
1"
b1 /
1#
b11111010 &
b11111010 *
#3840000
0#
#3850000
b100011101 !
b100011101 .
1"
b11 /
1#
b111110100 &
b111110100 *
#3860000
0#
#3870000
b100011110 !
b100011110 .
1"
b100 /
1#
b1011101110 &
b1011101110 *
#3880000
0#
#3890000
b100100000 !
b100100000 .
1"
b0 /
b100100000 -
1#
b0 &
b0 *
b110000 '
b110000 +
b110000 )
#3900000
0#
#3910000
b100100001 !
b100100001 .
1"
b1 /
1#
b11111010 &
b11111010 *
#3920000
0#
#3930000
b100100011 !
b100100011 .
1"
b11 /
1#
b111110100 &
b111110100 *
#3940000
0#
#3950000
b100100100 !
b100100100 .
1"
b100 /
1#
b1011101110 &
b1011101110 *
#3960000
0#
#3970000
b100100110 !
b100100110 .
1"
b0 /
b100100110 -
1#
b0 &
b0 *
b110001 '
b110001 +
b110001 )
#3980000
0#
#3990000
b100100111 !
b100100111 .
1"
b1 /
1#
b11111010 &
b11111010 *
#4000000
0#
#4010000
b100101001 !
b100101001 .
1"
b11 /
1#
b111110100 &
b111110100 *
#4020000
0#
#4030000
b100101010 !
b100101010 .
1"
b100 /
1#
b1011101110 &
b1011101110 *
#4040000
0#
#4050000
b100101100 !
b100101100 .
1"
b0 /
b100101100 -
1#
b0 &
b0 *
b110010 '
b110010 +
b110010 )
#4060000
0#
#4070000
b100101101 !
b100101101 .
1"
b1 /
1#
b11111010 &
b11111010 *
