project/rtl/crankshaft/crankshaft_position.v
module crankshaft_position #(
    parameter TOTAL_TEETH = 60,
    parameter PHYSICAL_TEETH = 58
)(
    input wire clk,
    input wire rst,
    input wire tooth_rise,
    input wire sync,

    output reg [$clog2(PHYSICAL_TEETH)-1:0] tooth_number,
    output reg [8:0] crankshaft_angle,
    output reg position_valid
);

    reg sync_active;

    always @(posedge clk) begin
        if (rst) begin
            tooth_number <= 0;
            crankshaft_angle <= 0;
            position_valid <= 0;
            sync_active <= 0;

        end else begin
            /*
             * Quando o sincronismo é encontrado, a ECU passa a conhecer a referência angular da roda fônica.
             * O sincronismo não deve zerar o contador de dentes, pois a contagem representa a posição atual do
             * virabrequim após a referência ser encontrada.
             */
            if (sync) begin
                sync_active <= 1;
            end
            /*
             * Antes do sincronismo ser encontrado, a ECU não sabe a posição absoluta do virabrequim.
             */
            if (!sync_active) begin
                position_valid <= 0;
            end 
            else begin
                position_valid <= 1;
                if (tooth_rise) begin
                    if (tooth_number < PHYSICAL_TEETH-1) begin
                        tooth_number <= tooth_number + 1;
                    end
                    else begin
                        tooth_number <= 0;
                    end


                    /*
                     * Converte o número do dente em posição angular. Uma roda 60-2 possui:
                     * 360 graus / 60 posições = 6 graus
                     * Mesmo existindo somente 58 dentes físicos,
                     * a referência angular continua sendo baseada
                     * nas 60 posições da roda.
                     */
                    if (tooth_number < PHYSICAL_TEETH-1) begin
                        crankshaft_angle <= (tooth_number + 1) * (360 / TOTAL_TEETH);
                    end
                    else begin
                        crankshaft_angle <= 0;
                    end
                end
            end
        end
    end
endmodule

project/sim/testbenches/engine_position/tb_crankshaft_position.v
`timescale 1ns/1ps

module tb_crankshaft_position;

    parameter CLK_PERIOD = 20;

    reg clk;
    reg rst;
    reg tooth_rise;
    reg sync;

    wire [5:0] tooth_number;
    wire [8:0] crankshaft_angle;
    wire position_valid;


    crankshaft_position dut (
        .clk(clk),
        .rst(rst),
        .tooth_rise(tooth_rise),
        .sync(sync),
        .tooth_number(tooth_number),
        .crankshaft_angle(crankshaft_angle),
        .position_valid(position_valid)
    );


    always #(CLK_PERIOD/2) clk = ~clk;


    task send_tooth;
        begin
            tooth_rise = 1;
            #(CLK_PERIOD);
            tooth_rise = 0;
            #(CLK_PERIOD);
        end
    endtask


    initial begin

        $dumpfile("tb_crankshaft_position.vcd");
        $dumpvars(0, tb_crankshaft_position);


        clk = 0;
        rst = 1;
        tooth_rise = 0;
        sync = 0;


        #(CLK_PERIOD*5);


        /*
         * Remove reset
         */
        rst = 0;


        /*
         * Sem sincronismo:
         * A posição deve permanecer inválida.
         */
        #(CLK_PERIOD*5);


        /*
         * Simula detecção da falha dos dentes.
         *
         * A partir deste ponto a ECU sabe
         * a referência angular.
         */
        sync = 1;


        #(CLK_PERIOD*5);


        /*
         * Simula os 58 dentes físicos
         * de uma roda 60-2.
         */
        repeat(58) begin
            send_tooth;

            $display(
                "Time=%0t | Tooth=%0d | Angle=%0d | Valid=%b",
                $time,
                tooth_number,
                crankshaft_angle,
                position_valid
            );
        end


        /*
         * Segunda volta:
         * verifica se o contador retorna para zero.
         */
        repeat(5) begin
            send_tooth;

            $display(
                "Time=%0t | Tooth=%0d | Angle=%0d | Valid=%b",
                $time,
                tooth_number,
                crankshaft_angle,
                position_valid
            );
        end


        #(CLK_PERIOD*10);


        $finish;

    end

endmodule

tb_crankshaft_position.vcd
$date
	Thu Jul 23 18:19:44 2026
$end
$version
	Icarus Verilog
$end
$timescale
	1ps
$end
$scope module tb_crankshaft_position $end
$var wire 6 ! tooth_number [5:0] $end
$var wire 1 " position_valid $end
$var wire 9 # crankshaft_angle [8:0] $end
$var reg 1 $ clk $end
$var reg 1 % rst $end
$var reg 1 & sync $end
$var reg 1 ' tooth_rise $end
$scope module dut $end
$var wire 1 $ clk $end
$var wire 1 % rst $end
$var wire 1 & sync $end
$var wire 1 ' tooth_rise $end
$var reg 9 ( crankshaft_angle [8:0] $end
$var reg 1 " position_valid $end
$var reg 1 ) sync_active $end
$var reg 6 * tooth_number [5:0] $end
$upscope $end
$scope task send_tooth $end
$upscope $end
$upscope $end
$enddefinitions $end
#0
$dumpvars
bx *
x)
bx (
0'
0&
1%
0$
bx #
x"
bx !
$end
#10000
0)
0"
b0 #
b0 (
b0 !
b0 *
1$
#20000
0$
#30000
1$
#40000
0$
#50000
1$
#60000
0$
#70000
1$
#80000
0$
#90000
1$
#100000
0$
0%
#110000
1$
#120000
0$
#130000
1$
#140000
0$
#150000
1$
#160000
0$
#170000
1$
#180000
0$
#190000
1$
#200000
0$
1&
#210000
1)
1$
#220000
0$
#230000
1"
1$
#240000
0$
#250000
1$
#260000
0$
#270000
1$
#280000
0$
#290000
1$
#300000
0$
1'
#310000
b110 #
b110 (
b1 !
b1 *
1$
#320000
0$
0'
#330000
1$
#340000
0$
1'
#350000
b1100 #
b1100 (
b10 !
b10 *
1$
#360000
0$
0'
#370000
1$
#380000
0$
1'
#390000
b10010 #
b10010 (
b11 !
b11 *
1$
#400000
0$
0'
#410000
1$
#420000
0$
1'
#430000
b11000 #
b11000 (
b100 !
b100 *
1$
#440000
0$
0'
#450000
1$
#460000
0$
1'
#470000
b11110 #
b11110 (
b101 !
b101 *
1$
#480000
0$
0'
#490000
1$
#500000
0$
1'
#510000
b100100 #
b100100 (
b110 !
b110 *
1$
#520000
0$
0'
#530000
1$
#540000
0$
1'
#550000
b101010 #
b101010 (
b111 !
b111 *
1$
#560000
0$
0'
#570000
1$
#580000
0$
1'
#590000
b110000 #
b110000 (
b1000 !
b1000 *
1$
#600000
0$
0'
#610000
1$
#620000
0$
1'
#630000
b110110 #
b110110 (
b1001 !
b1001 *
1$
#640000
0$
0'
#650000
1$
#660000
0$
1'
#670000
b111100 #
b111100 (
b1010 !
b1010 *
1$
#680000
0$
0'
#690000
1$
#700000
0$
1'
#710000
b1000010 #
b1000010 (
b1011 !
b1011 *
1$
#720000
0$
0'
#730000
1$
#740000
0$
1'
#750000
b1001000 #
b1001000 (
b1100 !
b1100 *
1$
#760000
0$
0'
#770000
1$
#780000
0$
1'
#790000
b1001110 #
b1001110 (
b1101 !
b1101 *
1$
#800000
0$
0'
#810000
1$
#820000
0$
1'
#830000
b1010100 #
b1010100 (
b1110 !
b1110 *
1$
#840000
0$
0'
#850000
1$
#860000
0$
1'
#870000
b1011010 #
b1011010 (
b1111 !
b1111 *
1$
#880000
0$
0'
#890000
1$
#900000
0$
1'
#910000
b1100000 #
b1100000 (
b10000 !
b10000 *
1$
#920000
0$
0'
#930000
1$
#940000
0$
1'
#950000
b1100110 #
b1100110 (
b10001 !
b10001 *
1$
#960000
0$
0'
#970000
1$
#980000
0$
1'
#990000
b1101100 #
b1101100 (
b10010 !
b10010 *
1$
#1000000
0$
0'
#1010000
1$
#1020000
0$
1'
#1030000
b1110010 #
b1110010 (
b10011 !
b10011 *
1$
#1040000
0$
0'
#1050000
1$
#1060000
0$
1'
#1070000
b1111000 #
b1111000 (
b10100 !
b10100 *
1$
#1080000
0$
0'
#1090000
1$
#1100000
0$
1'
#1110000
b1111110 #
b1111110 (
b10101 !
b10101 *
1$
#1120000
0$
0'
#1130000
1$
#1140000
0$
1'
#1150000
b10000100 #
b10000100 (
b10110 !
b10110 *
1$
#1160000
0$
0'
#1170000
1$
#1180000
0$
1'
#1190000
b10001010 #
b10001010 (
b10111 !
b10111 *
1$
#1200000
0$
0'
#1210000
1$
#1220000
0$
1'
#1230000
b10010000 #
b10010000 (
b11000 !
b11000 *
1$
#1240000
0$
0'
#1250000
1$
#1260000
0$
1'
#1270000
b10010110 #
b10010110 (
b11001 !
b11001 *
1$
#1280000
0$
0'
#1290000
1$
#1300000
0$
1'
#1310000
b10011100 #
b10011100 (
b11010 !
b11010 *
1$
#1320000
0$
0'
#1330000
1$
#1340000
0$
1'
#1350000
b10100010 #
b10100010 (
b11011 !
b11011 *
1$
#1360000
0$
0'
#1370000
1$
#1380000
0$
1'
#1390000
b10101000 #
b10101000 (
b11100 !
b11100 *
1$
#1400000
0$
0'
#1410000
1$
#1420000
0$
1'
#1430000
b10101110 #
b10101110 (
b11101 !
b11101 *
1$
#1440000
0$
0'
#1450000
1$
#1460000
0$
1'
#1470000
b10110100 #
b10110100 (
b11110 !
b11110 *
1$
#1480000
0$
0'
#1490000
1$
#1500000
0$
1'
#1510000
b10111010 #
b10111010 (
b11111 !
b11111 *
1$
#1520000
0$
0'
#1530000
1$
#1540000
0$
1'
#1550000
b11000000 #
b11000000 (
b100000 !
b100000 *
1$
#1560000
0$
0'
#1570000
1$
#1580000
0$
1'
#1590000
b11000110 #
b11000110 (
b100001 !
b100001 *
1$
#1600000
0$
0'
#1610000
1$
#1620000
0$
1'
#1630000
b11001100 #
b11001100 (
b100010 !
b100010 *
1$
#1640000
0$
0'
#1650000
1$
#1660000
0$
1'
#1670000
b11010010 #
b11010010 (
b100011 !
b100011 *
1$
#1680000
0$
0'
#1690000
1$
#1700000
0$
1'
#1710000
b11011000 #
b11011000 (
b100100 !
b100100 *
1$
#1720000
0$
0'
#1730000
1$
#1740000
0$
1'
#1750000
b11011110 #
b11011110 (
b100101 !
b100101 *
1$
#1760000
0$
0'
#1770000
1$
#1780000
0$
1'
#1790000
b11100100 #
b11100100 (
b100110 !
b100110 *
1$
#1800000
0$
0'
#1810000
1$
#1820000
0$
1'
#1830000
b11101010 #
b11101010 (
b100111 !
b100111 *
1$
#1840000
0$
0'
#1850000
1$
#1860000
0$
1'
#1870000
b11110000 #
b11110000 (
b101000 !
b101000 *
1$
#1880000
0$
0'
#1890000
1$
#1900000
0$
1'
#1910000
b11110110 #
b11110110 (
b101001 !
b101001 *
1$
#1920000
0$
0'
#1930000
1$
#1940000
0$
1'
#1950000
b11111100 #
b11111100 (
b101010 !
b101010 *
1$
#1960000
0$
0'
#1970000
1$
#1980000
0$
1'
#1990000
b100000010 #
b100000010 (
b101011 !
b101011 *
1$
#2000000
0$
0'
#2010000
1$
#2020000
0$
1'
#2030000
b100001000 #
b100001000 (
b101100 !
b101100 *
1$
#2040000
0$
0'
#2050000
1$
#2060000
0$
1'
#2070000
b100001110 #
b100001110 (
b101101 !
b101101 *
1$
#2080000
0$
0'
#2090000
1$
#2100000
0$
1'
#2110000
b100010100 #
b100010100 (
b101110 !
b101110 *
1$
#2120000
0$
0'
#2130000
1$
#2140000
0$
1'
#2150000
b100011010 #
b100011010 (
b101111 !
b101111 *
1$
#2160000
0$
0'
#2170000
1$
#2180000
0$
1'
#2190000
b100100000 #
b100100000 (
b110000 !
b110000 *
1$
#2200000
0$
0'
#2210000
1$
#2220000
0$
1'
#2230000
b100100110 #
b100100110 (
b110001 !
b110001 *
1$
#2240000
0$
0'
#2250000
1$
#2260000
0$
1'
#2270000
b100101100 #
b100101100 (
b110010 !
b110010 *
1$
#2280000
0$
0'
#2290000
1$
#2300000
0$
1'
#2310000
b100110010 #
b100110010 (
b110011 !
b110011 *
1$
#2320000
0$
0'
#2330000
1$
#2340000
0$
1'
#2350000
b100111000 #
b100111000 (
b110100 !
b110100 *
1$
#2360000
0$
0'
#2370000
1$
#2380000
0$
1'
#2390000
b100111110 #
b100111110 (
b110101 !
b110101 *
1$
#2400000
0$
0'
#2410000
1$
#2420000
0$
1'
#2430000
b101000100 #
b101000100 (
b110110 !
b110110 *
1$
#2440000
0$
0'
#2450000
1$
#2460000
0$
1'
#2470000
b101001010 #
b101001010 (
b110111 !
b110111 *
1$
#2480000
0$
0'
#2490000
1$
#2500000
0$
1'
#2510000
b101010000 #
b101010000 (
b111000 !
b111000 *
1$
#2520000
0$
0'
#2530000
1$
#2540000
0$
1'
#2550000
b101010110 #
b101010110 (
b111001 !
b111001 *
1$
#2560000
0$
0'
#2570000
1$
#2580000
0$
1'
#2590000
b0 #
b0 (
b0 !
b0 *
1$
#2600000
0$
0'
#2610000
1$
#2620000
0$
1'
#2630000
b110 #
b110 (
b1 !
b1 *
1$
#2640000
0$
0'
#2650000
1$
#2660000
0$
1'
#2670000
b1100 #
b1100 (
b10 !
b10 *
1$
#2680000
0$
0'
#2690000
1$
#2700000
0$
1'
#2710000
b10010 #
b10010 (
b11 !
b11 *
1$
#2720000
0$
0'
#2730000
1$
#2740000
0$
1'
#2750000
b11000 #
b11000 (
b100 !
b100 *
1$
#2760000
0$
0'
#2770000
1$
#2780000
0$
1'
#2790000
b11110 #
b11110 (
b101 !
b101 *
1$
#2800000
0$
0'
