pwm/pwm_generator.v
module pwm_generator #(
    parameter FREQ_HZ        = 50_000_000,
    parameter INITIAL_WIDTH  = 20,
    parameter INITIAL_PERIOD = 100,
    parameter STEP_CYCLES    = 1
)(
    input  wire clk,
    input  wire reset,

    output reg  out
);

    localparam [63:0] INIT_WIDTH_CYCLES =
        (64'd1 * FREQ_HZ * INITIAL_WIDTH) / 64'd1_000_000_000;

    localparam [63:0] INIT_PERIOD_CYCLES =
        (64'd1 * FREQ_HZ * INITIAL_PERIOD) / 64'd1_000_000_000;

    reg [63:0] counter;

    initial begin
        $display("INIT_WIDTH_CYCLES  = %0d", INIT_WIDTH_CYCLES);
        $display("INIT_PERIOD_CYCLES = %0d", INIT_PERIOD_CYCLES);
    end

    always @(posedge clk) begin
        if (reset) begin
            counter <= 64'd0;
            out     <= 1'b0;
        end
        else begin
            // Contador do período
            if (counter == (INIT_PERIOD_CYCLES - 1))
                counter <= 64'd0;
            else
                counter <= counter + 64'd1;

            // Geração do pulso
            if (counter < INIT_WIDTH_CYCLES)
                out <= 1'b1;
            else
                out <= 1'b0;
        end
    end

endmodule

// module gerador_pulso_total_controle #(
//     parameter FREQ_HZ       = 50000000, // Clock de 50 MHz (1 ciclo = 20 ns)
//     parameter INICIAL_LARG  = 20,       // Largura inicial em ns (20 ns = 1 ciclo)
//     parameter INICIAL_PER   = 100,      // Período inicial em ns (100 ns = 5 ciclos)
//     parameter PASSO_CICLOS  = 1         // Quantos ciclos de clock mudam a cada clique
// )(
//     input  wire clk,
//     input  wire reset,                  // Reset Síncrono
//     input  wire trigger,                // Se for 1: oscila o PWM. Se for 0: morre em 0.
    
//     // Botões para controlar o tempo em '1' (Largura)
//     input  wire btn_larg_inc,           
//     input  wire btn_larg_dec,           
    
//     // Botões para controlar o intervalo total (Período)
//     input  wire btn_per_inc,            
//     input  wire btn_per_dec,            
    
//     output reg  saida
// );

//     // Converte os valores iniciais de parâmetros (ns) para ciclos de clock na compilação
//     localparam [31:0] INIT_LARG_CICLOS = ( (FREQ_HZ * INICIAL_LARG) / 1000000000 );
//     localparam [31:0] INIT_PER_CICLOS  = ( (FREQ_HZ * INICIAL_PER) / 1000000000 );

//     // Registradores dinâmicos que guardam os limites de tempo atuais (alterados por botões)
//     reg [31:0] limite_largura; 
//     reg [31:0] limite_periodo; 

//     reg [31:0] contador;

//     // Registradores para detectar a borda de subida (clique único) de cada botão
//     reg larg_inc_r, larg_dec_r, per_inc_r, per_dec_r;

//     always @(posedge clk) begin
//         if (reset) begin
//             contador       <= 32'd0;
//             saida          <= 1'b0;
//             // Carrega os tempos iniciais de largura e período
//             limite_largura <= (INIT_LARG_CICLOS == 0) ? 32'd1 : INIT_LARG_CICLOS;
//             limite_periodo <= (INIT_PER_CICLOS == 0) ? 32'd2 : INIT_PER_CICLOS;
//             // Limpa registradores de borda
//             larg_inc_r     <= 1'b0; larg_dec_r <= 1'b0;
//             per_inc_r      <= 1'b0; per_dec_r  <= 1'b0;
//         end else begin
            
//             // 1. Amostragem dos botões para pegar apenas o instante do clique (borda)
//             larg_inc_r <= btn_larg_inc; larg_dec_r <= btn_larg_dec;
//             per_inc_r  <= btn_per_inc;  per_dec_r  <= btn_per_dec;

//             // 2. CONTROLE DA LARGURA (Tempo em '1')
//             if (btn_larg_inc && !larg_inc_r) begin
//                 // Não deixa a largura ficar maior ou igual ao período total
//                 if ((limite_largura + PASSO_CICLOS) < limite_periodo)
//                     limite_largura <= limite_largura + PASSO_CICLOS;
//             end
//             else if (btn_larg_dec && !larg_dec_r) begin
//                 // Garante largura mínima de pelo menos 1 ciclo de clock
//                 if (limite_largura > PASSO_CICLOS)
//                     limite_largura <= limite_largura - PASSO_CICLOS;
//             end

//             // 3. CONTROLE DO PERÍODO (Intervalo total de subida)
//             if (btn_per_inc && !per_inc_r) begin
//                 limite_periodo <= limite_periodo + PASSO_CICLOS;
//             end
//             else if (btn_per_dec && !per_dec_r) begin
//                 // Não deixa o período encolher a ponto de esmagar a largura configurada
//                 if (limite_periodo > (limite_largura + PASSO_CICLOS))
//                     limite_periodo <= limite_periodo - PASSO_CICLOS;
//             end

//             // 4. LÓGICA DE GERAÇÃO DA ONDA (Se o trigger estiver ativo)
//             if (trigger) begin
//                 // O contador dita o compasso do período total
//                 if (contador < (limite_periodo - 1)) begin
//                     contador <= contador + 1'b1;
//                 end else begin
//                     contador <= 32'd0; // Bateu o tempo total, reinicia o ciclo e sobe a onda
//                 end

//                 // Define a saída olhando puramente as regras de tempo em '1'
//                 if (contador < limite_largura) begin
//                     saida <= 1'b1; // Janela de tempo ativo
//                 end else begin
//                     saida <= 1'b0; // Janela de espera para a próxima subida
//                 end
//             end else begin
//                 // Se desligar o trigger, zera tudo imediatamente
//                 contador <= 32'd0;
//                 saida    <= 1'b0;
//             end

//         end
//     end

// endmodule

pwm/tb_pwm_generator.v
`timescale 1ns/1ps

module tb_pwm_generator;

    reg clk;
    reg reset;
    wire out;

    pwm_generator #(
        .FREQ_HZ(50000000),
        .INITIAL_WIDTH(20),
        .INITIAL_PERIOD(100),
        .STEP_CYCLES(1)
    ) dut (
        .clk(clk),
        .reset(reset),
        .out(out)
    );

    initial begin
        clk = 0;
        forever #10 clk = ~clk;   // Clock de 50 MHz (20 ns)
    end

    initial begin
        reset = 1;

        #40;
        reset = 0;

        #3000;

        $finish;
    end

    initial begin
        $dumpfile("tb_pwm_generator.vcd");
        $dumpvars(0, tb_pwm_generator);
    end

endmodule

pwm/tb_pwm_generator.vcd
$date
	Wed Jul 22 21:23:12 2026
$end
$version
	Icarus Verilog
$end
$timescale
	1ps
$end
$scope module tb_pwm_generator $end
$var wire 1 ! out $end
$var reg 1 " clk $end
$var reg 1 # reset $end
$scope module dut $end
$var wire 1 " clk $end
$var wire 1 # reset $end
$var reg 64 $ counter [63:0] $end
$var reg 1 ! out $end
$upscope $end
$upscope $end
$enddefinitions $end
#0
$dumpvars
bx $
1#
0"
x!
$end
#10000
0!
b0 $
1"
#20000
0"
#30000
1"
#40000
0"
0#
#50000
1!
b1 $
1"
#60000
0"
#70000
0!
b10 $
1"
#80000
0"
#90000
b11 $
1"
#100000
0"
#110000
b100 $
1"
#120000
0"
#130000
b0 $
1"
#140000
0"
#150000
1!
b1 $
1"
#160000
0"
#170000
0!
b10 $
1"
#180000
0"
#190000
b11 $
1"
#200000
0"
#210000
b100 $
1"
#220000
0"
#230000
b0 $
1"
#240000
0"
#250000
1!
b1 $
1"
#260000
0"
#270000
0!
b10 $
1"
#280000
0"
#290000
b11 $
1"
#300000
0"
#310000
b100 $
1"
#320000
0"
#330000
b0 $
1"
#340000
0"
#350000
1!
b1 $
1"
#360000
0"
#370000
0!
b10 $
1"
#380000
0"
#390000
b11 $
1"
#400000
0"
#410000
b100 $
1"
#420000
0"
#430000
b0 $
1"
#440000
0"
#450000
1!
b1 $
1"
#460000
0"
#470000
0!
b10 $
1"
#480000
0"
#490000
b11 $
1"
#500000
0"
#510000
b100 $
1"
#520000
0"
#530000
b0 $
1"
#540000
0"
#550000
1!
b1 $
1"
#560000
0"
#570000
0!
b10 $
1"
#580000
0"
#590000
b11 $
1"
#600000
0"
#610000
b100 $
1"
#620000
0"
#630000
b0 $
1"
#640000
0"
#650000
1!
b1 $
1"
#660000
0"
#670000
0!
b10 $
1"
#680000
0"
#690000
b11 $
1"
#700000
0"
#710000
b100 $
1"
#720000
0"
#730000
b0 $
1"
#740000
0"
#750000
1!
b1 $
1"
#760000
0"
#770000
0!
b10 $
1"
#780000
0"
#790000
b11 $
1"
#800000
0"
#810000
b100 $
1"
#820000
0"
#830000
b0 $
1"
#840000
0"
#850000
1!
b1 $
1"
#860000
0"
#870000
0!
b10 $
1"
#880000
0"
#890000
b11 $
1"
#900000
0"
#910000
b100 $
1"
#920000
0"
#930000
b0 $
1"
#940000
0"
#950000
1!
b1 $
1"
#960000
0"
#970000
0!
b10 $
1"
#980000
0"
#990000
b11 $
1"
#1000000
0"
#1010000
b100 $
1"
#1020000
0"
#1030000
b0 $
1"
#1040000
0"
#1050000
1!
b1 $
1"
#1060000
0"
#1070000
0!
b10 $
1"
#1080000
0"
#1090000
b11 $
1"
#1100000
0"
#1110000
b100 $
1"
#1120000
0"
#1130000
b0 $
1"
#1140000
0"
#1150000
1!
b1 $
1"
#1160000
0"
#1170000
0!
b10 $
1"
#1180000
0"
#1190000
b11 $
1"
#1200000
0"
#1210000
b100 $
1"
#1220000
0"
#1230000
b0 $
1"
#1240000
0"
#1250000
1!
b1 $
1"
#1260000
0"
#1270000
0!
b10 $
1"
#1280000
0"
#1290000
b11 $
1"
#1300000
0"
#1310000
b100 $
1"
#1320000
0"
#1330000
b0 $
1"
#1340000
0"
#1350000
1!
b1 $
1"
#1360000
0"
#1370000
0!
b10 $
1"
#1380000
0"
#1390000
b11 $
1"
#1400000
0"
#1410000
b100 $
1"
#1420000
0"
#1430000
b0 $
1"
#1440000
0"
#1450000
1!
b1 $
1"
#1460000
0"
#1470000
0!
b10 $
1"
#1480000
0"
#1490000
b11 $
1"
#1500000
0"
#1510000
b100 $
1"
#1520000
0"
#1530000
b0 $
1"
#1540000
0"
#1550000
1!
b1 $
1"
#1560000
0"
#1570000
0!
b10 $
1"
#1580000
0"
#1590000
b11 $
1"
#1600000
0"
#1610000
b100 $
1"
#1620000
0"
#1630000
b0 $
1"
#1640000
0"
#1650000
1!
b1 $
1"
#1660000
0"
#1670000
0!
b10 $
1"
#1680000
0"
#1690000
b11 $
1"
#1700000
0"
#1710000
b100 $
1"
#1720000
0"
#1730000
b0 $
1"
#1740000
0"
#1750000
1!
b1 $
1"
#1760000
0"
#1770000
0!
b10 $
1"
#1780000
0"
#1790000
b11 $
1"
#1800000
0"
#1810000
b100 $
1"
#1820000
0"
#1830000
b0 $
1"
#1840000
0"
#1850000
1!
b1 $
1"
#1860000
0"
#1870000
0!
b10 $
1"
#1880000
0"
#1890000
b11 $
1"
#1900000
0"
#1910000
b100 $
1"
#1920000
0"
#1930000
b0 $
1"
#1940000
0"
#1950000
1!
b1 $
1"
#1960000
0"
#1970000
0!
b10 $
1"
#1980000
0"
#1990000
b11 $
1"
#2000000
0"
#2010000
b100 $
1"
#2020000
0"
#2030000
b0 $
1"
#2040000
0"
#2050000
1!
b1 $
1"
#2060000
0"
#2070000
0!
b10 $
1"
#2080000
0"
#2090000
b11 $
1"
#2100000
0"
#2110000
b100 $
1"
#2120000
0"
#2130000
b0 $
1"
#2140000
0"
#2150000
1!
b1 $
1"
#2160000
0"
#2170000
0!
b10 $
1"
#2180000
0"
#2190000
b11 $
1"
#2200000
0"
#2210000
b100 $
1"
#2220000
0"
#2230000
b0 $
1"
#2240000
0"
#2250000
1!
b1 $
1"
#2260000
0"
#2270000
0!
b10 $
1"
#2280000
0"
#2290000
b11 $
1"
#2300000
0"
#2310000
b100 $
1"
#2320000
0"
#2330000
b0 $
1"
#2340000
0"
#2350000
1!
b1 $
1"
#2360000
0"
#2370000
0!
b10 $
1"
#2380000
0"
#2390000
b11 $
1"
#2400000
0"
#2410000
b100 $
1"
#2420000
0"
#2430000
b0 $
1"
#2440000
0"
#2450000
1!
b1 $
1"
#2460000
0"
#2470000
0!
b10 $
1"
#2480000
0"
#2490000
b11 $
1"
#2500000
0"
#2510000
b100 $
1"
#2520000
0"
#2530000
b0 $
1"
#2540000
0"
#2550000
1!
b1 $
1"
#2560000
0"
#2570000
0!
b10 $
1"
#2580000
0"
#2590000
b11 $
1"
#2600000
0"
#2610000
b100 $
1"
#2620000
0"
#2630000
b0 $
1"
#2640000
0"
#2650000
1!
b1 $
1"
#2660000
0"
#2670000
0!
b10 $
1"
#2680000
0"
#2690000
b11 $
1"
#2700000
0"
#2710000
b100 $
1"
#2720000
0"
#2730000
b0 $
1"
#2740000
0"
#2750000
1!
b1 $
1"
#2760000
0"
#2770000
0!
b10 $
1"
#2780000
0"
#2790000
b11 $
1"
#2800000
0"
#2810000
b100 $
1"
#2820000
0"
#2830000
b0 $
1"
#2840000
0"
#2850000
1!
b1 $
1"
#2860000
0"
#2870000
0!
b10 $
1"
#2880000
0"
#2890000
b11 $
1"
#2900000
0"
#2910000
b100 $
1"
#2920000
0"
#2930000
b0 $
1"
#2940000
0"
#2950000
1!
b1 $
1"
#2960000
0"
#2970000
0!
b10 $
1"
#2980000
0"
#2990000
b11 $
1"
#3000000
0"
#3010000
b100 $
1"
#3020000
0"
#3030000
b0 $
1"
